gestalt/__init__.py
gestalt/provider.py
gestalt/utils.py
gestalt/vault.py
tests/__init__.py
tests/conftest.py
tests/test_gestalt.py
tests/test_vault.py
yi_foo-0.0.2.dist-info/LICENSE
yi_foo-0.0.2.dist-info/METADATA
yi_foo-0.0.2.dist-info/WHEEL
yi_foo-0.0.2.dist-info/top_level.txt
yi_foo-0.0.2.dist-info/RECORD
