Metadata-Version: 2.1
Name: yi-foo
Version: 0.0.2
Summary: A foo package
Home-page: https://github.com/clear-street/foo
Author: Clear Street
Author-email: engineering@clearstreet.io
License: MIT
Platform: UNKNOWN
Classifier: Development Status :: 1 - Planning
Classifier: Intended Audience :: Developers
Classifier: License :: OSI Approved :: MIT License
Classifier: Topic :: Software Development :: Libraries
Classifier: Programming Language :: Python :: 3
Classifier: Programming Language :: Python :: 3.6
Classifier: Programming Language :: Python :: 3.7
Classifier: Programming Language :: Python :: 3.8
Classifier: Programming Language :: Python :: 3 :: Only
Classifier: Operating System :: OS Independent
Requires-Python: >=3.6
Requires-Dist: PyYAML (==5.4.1)
Requires-Dist: hvac (<1.1.0,>=1.0.2)
Requires-Dist: jsonpath-ng (==1.5.3)
Requires-Dist: retry (==0.9.2)
Requires-Dist: types-retry (==0.9.9)
